kpublicip/__init__.py
kpublicip/public_ip.py
kpublicip-0.0.2.dist-info/METADATA
kpublicip-0.0.2.dist-info/WHEEL
kpublicip-0.0.2.dist-info/top_level.txt
kpublicip-0.0.2.dist-info/RECORD
