Metadata-Version: 2.1
Name: kpublicip
Version: 0.0.2
Summary: get your public ipv4 or ipv6
Home-page: https://github.com/kkristof200/py_public_ip
Author: Kristof
License: UNKNOWN
Platform: UNKNOWN
Classifier: Programming Language :: Python :: 3
Classifier: License :: OSI Approved :: MIT License
Classifier: Operating System :: OS Independent
Requires-Python: >=3.5
Requires-Dist: requests
